krema/__init__.py
krema/errors.py
krema/gateway.py
krema/http.py
krema/types.py
krema/utils.py
krema/models/__init__.py
krema/models/channel.py
krema/models/client.py
krema/models/guild.py
krema/models/invite.py
krema/models/message.py
krema/models/sticker.py
krema/models/user.py
krema/models/webhook.py
krema-1.0.0.dist-info/LICENSE
krema-1.0.0.dist-info/METADATA
krema-1.0.0.dist-info/WHEEL
krema-1.0.0.dist-info/top_level.txt
krema-1.0.0.dist-info/RECORD
