Metadata-Version: 2.1
Name: krema
Version: 1.0.0
Summary: 🚀 A fast, flexible and lightweight Discord API wrapper for Python.
Home-page: https://github.com/kremayard/krema/
Author: kremayard
Author-email: 
License: MIT
Project-URL: Bug Tracker, https://github.com/kremayard/krema/issues
Keywords: python,krema,discord,discord-api,api-wrapper
Platform: UNKNOWN
Classifier: Development Status :: 5 - Production/Stable
Classifier: Intended Audience :: Developers
Classifier: Operating System :: OS Independent
Classifier: License :: OSI Approved :: MIT License
Classifier: Programming Language :: Python :: 3
Requires-Python: >=3.8.0
Requires-Dist: kollektor
